{"trip_id":"weekday_U2220_U222002_3","arrival_time":"19:45:00","departure_time":"19:45:00","stop_id":"1001259","stop_sequence":"1","stop_headsign":"Lrt Wangsa Maju"},
{"trip_id":"weekday_U2220_U222002_3","arrival_time":"19:45:52","departure_time":"19:45:52","stop_id":"1000355","stop_sequence":"2","stop_headsign":"Lrt Wangsa Maju"},
{"trip_id":"weekday_U2220_U222002_3","arrival_time":"19:47:25","departure_time":"19:47:25","stop_id":"1002285","stop_sequence":"3","stop_headsign":"Lrt Wangsa Maju"},
{"trip_id":"weekday_U2220_U222002_3","arrival_time":"19:48:37","departure_time":"19:48:37","stop_id":"1003835","stop_sequence":"4","stop_headsign":"Lrt Wangsa Maju"},
{"trip_id":"weekday_U2220_U222002_3","arrival_time":"19:52:02","departure_time":"19:52:02","stop_id":"1003099","stop_sequence":"5","stop_headsign":"Lrt Wangsa Maju"},
{"trip_id":"weekday_U2220_U222002_3","arrival_time":"19:53:37","departure_time":"19:53:37","stop_id":"1000498","stop_sequence":"6","stop_headsign":"Lrt Wangsa Maju"},
{"trip_id":"weekday_U2220_U222002_3","arrival_time":"19:55:44","departure_time":"19:55:44","stop_id":"1006121","stop_sequence":"7","stop_headsign":"Lrt Wangsa Maju"},
{"trip_id":"weekday_U2220_U222002_3","arrival_time":"19:57:06","departure_time":"19:57:06","stop_id":"1003410","stop_sequence":"8","stop_headsign":"Lrt Wangsa Maju"},
{"trip_id":"weekday_U2220_U222002_3","arrival_time":"19:58:17","departure_time":"19:58:17","stop_id":"1002231","stop_sequence":"9","stop_headsign":"Lrt Wangsa Maju"},
{"trip_id":"weekday_U2220_U222002_3","arrival_time":"19:59:30","departure_time":"19:59:30","stop_id":"1000663","stop_sequence":"10","stop_headsign":"Lrt Wangsa Maju"},
{"trip_id":"weekday_U2220_U222002_3","arrival_time":"20:00:59","departure_time":"20:00:59","stop_id":"1007533","stop_sequence":"11","stop_headsign":"Lrt Wangsa Maju"},
{"trip_id":"weekday_U2220_U222002_3","arrival_time":"20:01:53","departure_time":"20:01:53","stop_id":"1000664","stop_sequence":"12","stop_headsign":"Lrt Wangsa Maju"},
{"trip_id":"weekday_U2220_U222002_3","arrival_time":"20:02:32","departure_time":"20:02:32","stop_id":"1007534","stop_sequence":"13","stop_headsign":"Lrt Wangsa Maju"},
{"trip_id":"weekday_U2220_U222002_3","arrival_time":"20:03:19","departure_time":"20:03:19","stop_id":"1003472","stop_sequence":"14","stop_headsign":"Lrt Wangsa Maju"},
{"trip_id":"weekday_U2220_U222002_3","arrival_time":"20:04:12","departure_time":"20:04:12","stop_id":"1003073","stop_sequence":"15","stop_headsign":"Lrt Wangsa Maju"},
{"trip_id":"weekday_U2220_U222002_3","arrival_time":"20:04:57","departure_time":"20:04:57","stop_id":"1003885","stop_sequence":"16","stop_headsign":"Lrt Wangsa Maju"},
{"trip_id":"weekday_U2220_U222002_3","arrival_time":"20:06:46","departure_time":"20:06:46","stop_id":"1000868","stop_sequence":"17","stop_headsign":"Lrt Wangsa Maju"},
{"trip_id":"weekday_U2220_U222002_3","arrival_time":"20:08:44","departure_time":"20:08:44","stop_id":"1002463","stop_sequence":"18","stop_headsign":"Lrt Wangsa Maju"},
{"trip_id":"weekday_U2220_U222002_3","arrival_time":"20:09:38","departure_time":"20:09:38","stop_id":"1003775","stop_sequence":"19","stop_headsign":"Lrt Wangsa Maju"},
{"trip_id":"weekday_U2220_U222002_3","arrival_time":"20:13:56","departure_time":"20:13:56","stop_id":"1001835","stop_sequence":"20","stop_headsign":"TAMAN MELAWATI"},
{"trip_id":"weekday_U2220_U222002_3","arrival_time":"20:14:59","departure_time":"20:14:59","stop_id":"1000750","stop_sequence":"21","stop_headsign":"TAMAN MELAWATI"},
{"trip_id":"weekday_U2220_U222002_3","arrival_time":"20:19:17","departure_time":"20:19:17","stop_id":"1003848","stop_sequence":"22","stop_headsign":"TAMAN MELAWATI"},
{"trip_id":"weekday_U2220_U222002_3","arrival_time":"20:20:20","departure_time":"20:20:20","stop_id":"1001834","stop_sequence":"23","stop_headsign":"TAMAN MELAWATI"},
{"trip_id":"weekday_U2220_U222002_3","arrival_time":"20:20:53","departure_time":"20:20:53","stop_id":"1000551","stop_sequence":"24","stop_headsign":"TAMAN MELAWATI"},
{"trip_id":"weekday_U2220_U222002_3","arrival_time":"20:24:34","departure_time":"20:24:34","stop_id":"1006132","stop_sequence":"25","stop_headsign":"TAMAN MELAWATI"},
{"trip_id":"weekday_U2220_U222002_3","arrival_time":"20:25:20","departure_time":"20:25:20","stop_id":"1002462","stop_sequence":"26","stop_headsign":"TAMAN MELAWATI"},
{"trip_id":"weekday_U2220_U222002_3","arrival_time":"20:27:14","departure_time":"20:27:14","stop_id":"1001368","stop_sequence":"27","stop_headsign":"TAMAN MELAWATI"},
{"trip_id":"weekday_U2220_U222002_3","arrival_time":"20:29:17","departure_time":"20:29:17","stop_id":"1000430","stop_sequence":"28","stop_headsign":"TAMAN MELAWATI"},
{"trip_id":"weekday_U2220_U222002_3","arrival_time":"20:30:17","departure_time":"20:30:17","stop_id":"1006122","stop_sequence":"29","stop_headsign":"TAMAN MELAWATI"},
{"trip_id":"weekday_U2220_U222002_3","arrival_time":"20:30:59","departure_time":"20:30:59","stop_id":"1000543","stop_sequence":"30","stop_headsign":"TAMAN MELAWATI"},
{"trip_id":"weekday_U2220_U222002_3","arrival_time":"20:32:29","departure_time":"20:32:29","stop_id":"1000497","stop_sequence":"31","stop_headsign":"TAMAN MELAWATI"},
{"trip_id":"weekday_U2220_U222002_3","arrival_time":"20:34:33","departure_time":"20:34:33","stop_id":"1003098","stop_sequence":"32","stop_headsign":"TAMAN MELAWATI"},
{"trip_id":"weekday_U2220_U222002_3","arrival_time":"20:36:07","departure_time":"20:36:07","stop_id":"1003835","stop_sequence":"33","stop_headsign":"TAMAN MELAWATI"},
{"trip_id":"weekday_U2220_U222002_3","arrival_time":"20:38:29","departure_time":"20:38:29","stop_id":"1002734","stop_sequence":"34","stop_headsign":"TAMAN MELAWATI"},
{"trip_id":"weekday_U2220_U222002_3","arrival_time":"20:39:54","departure_time":"20:39:54","stop_id":"1003069","stop_sequence":"35","stop_headsign":"TAMAN MELAWATI"},
{"trip_id":"weekday_U2220_U222002_3","arrival_time":"20:41:41","departure_time":"20:41:41","stop_id":"1003663","stop_sequence":"36","stop_headsign":"TAMAN MELAWATI"},
{"trip_id":"weekday_U2220_U222002_3","arrival_time":"20:42:44","departure_time":"20:42:44","stop_id":"1003827","stop_sequence":"37","stop_headsign":"TAMAN MELAWATI"},
{"trip_id":"weekday_U2220_U222002_3","arrival_time":"20:43:58","departure_time":"20:43:58","stop_id":"1000852","stop_sequence":"38","stop_headsign":"TAMAN MELAWATI"},
{"trip_id":"weekday_U2220_U222002_3","arrival_time":"20:45:00","departure_time":"20:45:00","stop_id":"1001259","stop_sequence":"39","stop_headsign":"TAMAN MELAWATI"}